annbatch/__init__.py
annbatch/compat.py
annbatch/io.py
annbatch/loader.py
annbatch/types.py
annbatch/utils.py
annbatch/abc/__init__.py
annbatch/abc/sampler.py
annbatch/samplers/__init__.py
annbatch/samplers/_chunk_sampler.py
annbatch-0.0.6.dist-info/METADATA
annbatch-0.0.6.dist-info/WHEEL
annbatch-0.0.6.dist-info/licenses/LICENSE
annbatch-0.0.6.dist-info/RECORD
