Metadata-Version: 2.4
Name: annbatch
Version: 0.0.6
Summary: A minibatch loader for AnnData stores
Project-URL: Documentation, https://annbatch.readthedocs.io/
Project-URL: Homepage, https://github.com/scverse/annbatch
Project-URL: Source, https://github.com/scverse/annbatch
Author: Ilan Gold, Felix Fischer
Maintainer-email: Ilan Gold <ilan.gold@scverse.org>, Felix Fischer <felix.fischer@lamin.ai>
License: MIT License
License-File: LICENSE
Classifier: Programming Language :: Python :: 3 :: Only
Classifier: Programming Language :: Python :: 3.12
Classifier: Programming Language :: Python :: 3.13
Requires-Python: <3.14,>=3.12
Requires-Dist: anndata[lazy]>=0.12.6
Requires-Dist: dask>=2025.9
Requires-Dist: pandas>=2.2.2
Requires-Dist: scipy>1.15
Requires-Dist: session-info2
Requires-Dist: tqdm
Requires-Dist: zarr>=3.1.4
Provides-Extra: cupy-cuda12
Requires-Dist: cupy-cuda12x; extra == 'cupy-cuda12'
Provides-Extra: cupy-cuda13
Requires-Dist: cupy-cuda13x; extra == 'cupy-cuda13'
Provides-Extra: dev
Requires-Dist: pre-commit; extra == 'dev'
Requires-Dist: twine>=4.0.2; extra == 'dev'
Provides-Extra: doc
Requires-Dist: docutils!=0.18.*,!=0.19.*,>=0.8; extra == 'doc'
Requires-Dist: ipykernel; extra == 'doc'
Requires-Dist: ipython; extra == 'doc'
Requires-Dist: myst-nb>=1.1; extra == 'doc'
Requires-Dist: pandas; extra == 'doc'
Requires-Dist: scanpydoc[theme,typehints]>=0.15.3; extra == 'doc'
Requires-Dist: sphinx-autodoc-typehints; extra == 'doc'
Requires-Dist: sphinx-book-theme>=1; extra == 'doc'
Requires-Dist: sphinx-copybutton; extra == 'doc'
Requires-Dist: sphinx-issues>=5.0.1; extra == 'doc'
Requires-Dist: sphinx-tabs; extra == 'doc'
Requires-Dist: sphinx-toolbox>=3.8; extra == 'doc'
Requires-Dist: sphinx<=8.2.3,>=8.1; extra == 'doc'
Requires-Dist: sphinxcontrib-bibtex>=1; extra == 'doc'
Requires-Dist: sphinxext-opengraph; extra == 'doc'
Provides-Extra: test
Requires-Dist: coverage; extra == 'test'
Requires-Dist: pytest; extra == 'test'
Requires-Dist: zarrs>=0.2.1; extra == 'test'
Provides-Extra: torch
Requires-Dist: torch>=2; extra == 'torch'
Provides-Extra: zarrs
Requires-Dist: zarrs>=0.2.1; extra == 'zarrs'
